[
    {
        "date": "2024-11-21",
        "symbol": "CPRT",
        "actualEarningResult": 0.37,
        "estimatedEarning": 0.37
    },
    {
        "date": "2024-09-04",
        "symbol": "CPRT",
        "actualEarningResult": 0.33,
        "estimatedEarning": 0.36
    },
    {
        "date": "2024-05-16",
        "symbol": "CPRT",
        "actualEarningResult": 0.39,
        "estimatedEarning": 0.39
    },
    {
        "date": "2024-02-22",
        "symbol": "CPRT",
        "actualEarningResult": 0.33,
        "estimatedEarning": 0.35
    },
    {
        "date": "2023-11-16",
        "symbol": "CPRT",
        "actualEarningResult": 0.34,
        "estimatedEarning": 0.33
    },
    {
        "date": "2023-09-14",
        "symbol": "CPRT",
        "actualEarningResult": 0.34,
        "estimatedEarning": 0.32
    },
    {
        "date": "2023-05-17",
        "symbol": "CPRT",
        "actualEarningResult": 0.36,
        "estimatedEarning": 0.31
    },
    {
        "date": "2023-02-20",
        "symbol": "CPRT",
        "actualEarningResult": 0.31,
        "estimatedEarning": 0.28
    },
    {
        "date": "2022-11-16",
        "symbol": "CPRT",
        "actualEarningResult": 0.26,
        "estimatedEarning": 0.28
    },
    {
        "date": "2022-09-07",
        "symbol": "CPRT",
        "actualEarningResult": 0.28,
        "estimatedEarning": 0.27
    },
    {
        "date": "2022-05-18",
        "symbol": "CPRT",
        "actualEarningResult": 0.29,
        "estimatedEarning": 0.29
    },
    {
        "date": "2022-02-16",
        "symbol": "CPRT",
        "actualEarningResult": 0.28,
        "estimatedEarning": 0.26
    },
    {
        "date": "2021-11-17",
        "symbol": "CPRT",
        "actualEarningResult": 0.27,
        "estimatedEarning": 0.25
    },
    {
        "date": "2021-09-08",
        "symbol": "CPRT",
        "actualEarningResult": 0.26,
        "estimatedEarning": 0.22
    },
    {
        "date": "2021-05-19",
        "symbol": "CPRT",
        "actualEarningResult": 0.27,
        "estimatedEarning": 0.2
    },
    {
        "date": "2021-02-18",
        "symbol": "CPRT",
        "actualEarningResult": 0.2,
        "estimatedEarning": 0.2
    },
    {
        "date": "2020-11-18",
        "symbol": "CPRT",
        "actualEarningResult": 0.2,
        "estimatedEarning": 0.17
    },
    {
        "date": "2020-09-02",
        "symbol": "CPRT",
        "actualEarningResult": 0.17,
        "estimatedEarning": 0.1
    },
    {
        "date": "2020-05-20",
        "symbol": "CPRT",
        "actualEarningResult": 0.15,
        "estimatedEarning": 0.16
    },
    {
        "date": "2020-02-19",
        "symbol": "CPRT",
        "actualEarningResult": 0.16,
        "estimatedEarning": 0.16
    },
    {
        "date": "2019-11-20",
        "symbol": "CPRT",
        "actualEarningResult": 0.16,
        "estimatedEarning": 0.15
    },
    {
        "date": "2019-09-04",
        "symbol": "CPRT",
        "actualEarningResult": 0.15,
        "estimatedEarning": 0.14
    },
    {
        "date": "2019-05-22",
        "symbol": "CPRT",
        "actualEarningResult": 0.17,
        "estimatedEarning": 0.15
    },
    {
        "date": "2019-02-20",
        "symbol": "CPRT",
        "actualEarningResult": 0.13,
        "estimatedEarning": 0.13
    },
    {
        "date": "2018-11-20",
        "symbol": "CPRT",
        "actualEarningResult": 0.12,
        "estimatedEarning": 0.12
    },
    {
        "date": "2018-09-19",
        "symbol": "CPRT",
        "actualEarningResult": 0.11,
        "estimatedEarning": 0.12
    },
    {
        "date": "2018-05-23",
        "symbol": "CPRT",
        "actualEarningResult": 0.13,
        "estimatedEarning": 0.12
    },
    {
        "date": "2018-02-26",
        "symbol": "CPRT",
        "actualEarningResult": 0.12,
        "estimatedEarning": 0.1
    },
    {
        "date": "2017-11-21",
        "symbol": "CPRT",
        "actualEarningResult": 0.08,
        "estimatedEarning": 0.07
    },
    {
        "date": "2017-09-19",
        "symbol": "CPRT",
        "actualEarningResult": 0.09,
        "estimatedEarning": 0.08
    },
    {
        "date": "2017-05-24",
        "symbol": "CPRT",
        "actualEarningResult": 0.09,
        "estimatedEarning": 0.09
    },
    {
        "date": "2017-02-21",
        "symbol": "CPRT",
        "actualEarningResult": 0.07,
        "estimatedEarning": 0.07
    },
    {
        "date": "2016-11-21",
        "symbol": "CPRT",
        "actualEarningResult": 0.07,
        "estimatedEarning": 0.07
    },
    {
        "date": "2016-09-20",
        "symbol": "CPRT",
        "actualEarningResult": 0.07,
        "estimatedEarning": 0.07
    },
    {
        "date": "2016-05-25",
        "symbol": "CPRT",
        "actualEarningResult": 0.08,
        "estimatedEarning": 0.07
    },
    {
        "date": "2016-02-23",
        "symbol": "CPRT",
        "actualEarningResult": 0.06,
        "estimatedEarning": 0.06
    },
    {
        "date": "2015-11-23",
        "symbol": "CPRT",
        "actualEarningResult": 0.05,
        "estimatedEarning": 0.05
    },
    {
        "date": "2015-09-22",
        "symbol": "CPRT",
        "actualEarningResult": 0.06,
        "estimatedEarning": 0.05
    },
    {
        "date": "2015-05-27",
        "symbol": "CPRT",
        "actualEarningResult": 0.06,
        "estimatedEarning": 0.06
    },
    {
        "date": "2015-02-24",
        "symbol": "CPRT",
        "actualEarningResult": 0.05,
        "estimatedEarning": 0.05
    },
    {
        "date": "2014-11-24",
        "symbol": "CPRT",
        "actualEarningResult": 0.05,
        "estimatedEarning": 0.05
    },
    {
        "date": "2014-09-23",
        "symbol": "CPRT",
        "actualEarningResult": 0.05,
        "estimatedEarning": 0.05
    },
    {
        "date": "2014-05-28",
        "symbol": "CPRT",
        "actualEarningResult": 0.06,
        "estimatedEarning": 0.06
    },
    {
        "date": "2014-02-25",
        "symbol": "CPRT",
        "actualEarningResult": 0.05,
        "estimatedEarning": 0.05
    },
    {
        "date": "2013-11-25",
        "symbol": "CPRT",
        "actualEarningResult": 0.04,
        "estimatedEarning": 0.03987
    },
    {
        "date": "2013-09-24",
        "symbol": "CPRT",
        "actualEarningResult": 0.04,
        "estimatedEarning": 0.05
    },
    {
        "date": "2013-05-30",
        "symbol": "CPRT",
        "actualEarningResult": 0.05,
        "estimatedEarning": 0.06
    },
    {
        "date": "2013-02-27",
        "symbol": "CPRT",
        "actualEarningResult": 0.05,
        "estimatedEarning": 0.05
    },
    {
        "date": "2012-11-27",
        "symbol": "CPRT",
        "actualEarningResult": 0.05,
        "estimatedEarning": 0.05
    },
    {
        "date": "2012-09-25",
        "symbol": "CPRT",
        "actualEarningResult": 0.09,
        "estimatedEarning": 0.08
    },
    {
        "date": "2012-05-29",
        "symbol": "CPRT",
        "actualEarningResult": 0.11,
        "estimatedEarning": 0.11
    },
    {
        "date": "2012-02-28",
        "symbol": "CPRT",
        "actualEarningResult": 0.09,
        "estimatedEarning": 0.07
    },
    {
        "date": "2011-11-28",
        "symbol": "CPRT",
        "actualEarningResult": 0.08,
        "estimatedEarning": 0.07
    },
    {
        "date": "2011-09-20",
        "symbol": "CPRT",
        "actualEarningResult": 0.07,
        "estimatedEarning": 0.07
    },
    {
        "date": "2011-06-01",
        "symbol": "CPRT",
        "actualEarningResult": 0.09,
        "estimatedEarning": 0.09
    },
    {
        "date": "2011-03-02",
        "symbol": "CPRT",
        "actualEarningResult": 0.06,
        "estimatedEarning": 0.06
    },
    {
        "date": "2010-11-30",
        "symbol": "CPRT",
        "actualEarningResult": 0.06,
        "estimatedEarning": 0.06
    },
    {
        "date": "2010-09-22",
        "symbol": "CPRT",
        "actualEarningResult": 0.05,
        "estimatedEarning": 0.06
    },
    {
        "date": "2010-06-02",
        "symbol": "CPRT",
        "actualEarningResult": 0.07,
        "estimatedEarning": 0.06
    },
    {
        "date": "2010-03-02",
        "symbol": "CPRT",
        "actualEarningResult": 0.05,
        "estimatedEarning": 0.05
    },
    {
        "date": "2009-12-01",
        "symbol": "CPRT",
        "actualEarningResult": 0.05,
        "estimatedEarning": 0.05
    },
    {
        "date": "2009-09-23",
        "symbol": "CPRT",
        "actualEarningResult": 0.05,
        "estimatedEarning": 0.05
    },
    {
        "date": "2009-06-03",
        "symbol": "CPRT",
        "actualEarningResult": 0.06,
        "estimatedEarning": 0.06
    },
    {
        "date": "2009-03-04",
        "symbol": "CPRT",
        "actualEarningResult": 0.04,
        "estimatedEarning": 0.05
    },
    {
        "date": "2008-12-03",
        "symbol": "CPRT",
        "actualEarningResult": 0.06,
        "estimatedEarning": 0.05
    },
    {
        "date": "2008-09-24",
        "symbol": "CPRT",
        "actualEarningResult": 0.06,
        "estimatedEarning": 0.06
    },
    {
        "date": "2008-06-03",
        "symbol": "CPRT",
        "actualEarningResult": 0.07,
        "estimatedEarning": 0.06
    },
    {
        "date": "2008-03-06",
        "symbol": "CPRT",
        "actualEarningResult": 0.04,
        "estimatedEarning": 0.05
    },
    {
        "date": "2007-12-04",
        "symbol": "CPRT",
        "actualEarningResult": 0.05,
        "estimatedEarning": 0.05
    },
    {
        "date": "2007-09-26",
        "symbol": "CPRT",
        "actualEarningResult": 0.05,
        "estimatedEarning": 0.04391
    },
    {
        "date": "2007-06-05",
        "symbol": "CPRT",
        "actualEarningResult": 0.05,
        "estimatedEarning": 0.05
    },
    {
        "date": "2007-03-06",
        "symbol": "CPRT",
        "actualEarningResult": 0.04,
        "estimatedEarning": 0.04143
    },
    {
        "date": "2006-12-05",
        "symbol": "CPRT",
        "actualEarningResult": 0.04,
        "estimatedEarning": 0.038
    },
    {
        "date": "2006-10-04",
        "symbol": "CPRT",
        "actualEarningResult": 0.04,
        "estimatedEarning": 0.03568
    },
    {
        "date": "2006-05-31",
        "symbol": "CPRT",
        "actualEarningResult": 0.05,
        "estimatedEarning": 0.05
    },
    {
        "date": "2006-03-07",
        "symbol": "CPRT",
        "actualEarningResult": 0.04,
        "estimatedEarning": 0.03828
    },
    {
        "date": "2005-12-02",
        "symbol": "CPRT",
        "actualEarningResult": 0.03,
        "estimatedEarning": 0.0324
    },
    {
        "date": "2005-09-28",
        "symbol": "CPRT",
        "actualEarningResult": 0.03,
        "estimatedEarning": 0.02889
    },
    {
        "date": "2005-06-01",
        "symbol": "CPRT",
        "actualEarningResult": 0.04,
        "estimatedEarning": 0.03709
    },
    {
        "date": "2005-03-01",
        "symbol": "CPRT",
        "actualEarningResult": 0.03,
        "estimatedEarning": 0.02664
    },
    {
        "date": "2004-11-30",
        "symbol": "CPRT",
        "actualEarningResult": 0.03,
        "estimatedEarning": 0.02594
    },
    {
        "date": "2004-09-14",
        "symbol": "CPRT",
        "actualEarningResult": 0.03,
        "estimatedEarning": 0.02786
    },
    {
        "date": "2004-05-25",
        "symbol": "CPRT",
        "actualEarningResult": 0.03,
        "estimatedEarning": 0.02278
    },
    {
        "date": "2004-02-24",
        "symbol": "CPRT",
        "actualEarningResult": 0.02,
        "estimatedEarning": 0.0172
    },
    {
        "date": "2003-12-02",
        "symbol": "CPRT",
        "actualEarningResult": 0.02,
        "estimatedEarning": 0.01882
    },
    {
        "date": "2003-09-16",
        "symbol": "CPRT",
        "actualEarningResult": 0.02,
        "estimatedEarning": 0.01867
    },
    {
        "date": "2003-05-21",
        "symbol": "CPRT",
        "actualEarningResult": 0.02,
        "estimatedEarning": 0.01804
    },
    {
        "date": "2003-02-18",
        "symbol": "CPRT",
        "actualEarningResult": 0.02,
        "estimatedEarning": 0.02133
    },
    {
        "date": "2002-11-20",
        "symbol": "CPRT",
        "actualEarningResult": 0.02,
        "estimatedEarning": 0.02
    },
    {
        "date": "2002-09-17",
        "symbol": "CPRT",
        "actualEarningResult": 0.02,
        "estimatedEarning": 0.02
    },
    {
        "date": "2002-05-21",
        "symbol": "CPRT",
        "actualEarningResult": 0.02,
        "estimatedEarning": 0.01904
    },
    {
        "date": "2002-02-25",
        "symbol": "CPRT",
        "actualEarningResult": 0.02,
        "estimatedEarning": 0.02
    },
    {
        "date": "2001-11-26",
        "symbol": "CPRT",
        "actualEarningResult": 0.02,
        "estimatedEarning": 0.01819
    },
    {
        "date": "2001-09-17",
        "symbol": "CPRT",
        "actualEarningResult": 0.02,
        "estimatedEarning": 0.01797
    },
    {
        "date": "2001-05-29",
        "symbol": "CPRT",
        "actualEarningResult": 0.02,
        "estimatedEarning": 0.01594
    },
    {
        "date": "2001-02-26",
        "symbol": "CPRT",
        "actualEarningResult": 0.0069,
        "estimatedEarning": 0.00629
    },
    {
        "date": "2000-11-27",
        "symbol": "CPRT",
        "actualEarningResult": 0.00658,
        "estimatedEarning": 0.00617
    },
    {
        "date": "2000-09-18",
        "symbol": "CPRT",
        "actualEarningResult": 0.00627,
        "estimatedEarning": 0.00616
    },
    {
        "date": "2000-05-30",
        "symbol": "CPRT",
        "actualEarningResult": 0.00615,
        "estimatedEarning": 0.00554
    },
    {
        "date": "2000-02-28",
        "symbol": "CPRT",
        "actualEarningResult": 0.00489,
        "estimatedEarning": 0.00455
    },
    {
        "date": "1999-11-29",
        "symbol": "CPRT",
        "actualEarningResult": 0.005,
        "estimatedEarning": 0.00457
    },
    {
        "date": "1999-09-21",
        "symbol": "CPRT",
        "actualEarningResult": 0.00497,
        "estimatedEarning": 0.00483
    },
    {
        "date": "1999-06-01",
        "symbol": "CPRT",
        "actualEarningResult": 0.005,
        "estimatedEarning": 0.00427
    },
    {
        "date": "1999-03-02",
        "symbol": "CPRT",
        "actualEarningResult": 0.00375,
        "estimatedEarning": 0.00334
    },
    {
        "date": "1998-12-01",
        "symbol": "CPRT",
        "actualEarningResult": 0.00333,
        "estimatedEarning": 0.00315
    },
    {
        "date": "1998-09-21",
        "symbol": "CPRT",
        "actualEarningResult": 0.00301,
        "estimatedEarning": 0.00279
    },
    {
        "date": "1998-06-08",
        "symbol": "CPRT",
        "actualEarningResult": 0.00334,
        "estimatedEarning": 0.00303
    },
    {
        "date": "1998-03-02",
        "symbol": "CPRT",
        "actualEarningResult": 0.00292,
        "estimatedEarning": 0.01
    },
    {
        "date": "1997-10-07",
        "symbol": "CPRT",
        "actualEarningResult": 0.00249,
        "estimatedEarning": 0.00262
    },
    {
        "date": "1997-06-02",
        "symbol": "CPRT",
        "actualEarningResult": 0.00292,
        "estimatedEarning": 0.01
    },
    {
        "date": "1997-03-11",
        "symbol": "CPRT",
        "actualEarningResult": 0.0025,
        "estimatedEarning": 0.00246
    },
    {
        "date": "1996-12-10",
        "symbol": "CPRT",
        "actualEarningResult": 0.00208,
        "estimatedEarning": 0.00272
    },
    {
        "date": "1996-10-08",
        "symbol": "CPRT",
        "actualEarningResult": 0.00253,
        "estimatedEarning": 0.0025
    }
]